ailuropoda/__init__.py
ailuropoda/__main__.py
ailuropoda/cbor_codegen.py
ailuropoda/main.py
cbor_codegen_deps-0.1.0.dist-info/licenses/LICENSE
cbor_codegen_deps-0.1.0.dist-info/METADATA
cbor_codegen_deps-0.1.0.dist-info/WHEEL
cbor_codegen_deps-0.1.0.dist-info/top_level.txt
cbor_codegen_deps-0.1.0.dist-info/RECORD
