Metadata-Version: 2.4
Name: cbor-codegen-deps
Version: 0.1.0
Summary: Dependencies for CBOR code generation
License: BSD-3-Clause
Classifier: License :: OSI Approved :: BSD License
Requires-Python: >=3.8
License-File: LICENSE
Requires-Dist: jinja2>=3.1.6
Requires-Dist: pycparser>=2.22
Dynamic: license-file
